README.rst
setup.py
z2labelmap/__init__.py
z2labelmap/z2labelmap.py
z2labelmap.egg-info/PKG-INFO
z2labelmap.egg-info/SOURCES.txt
z2labelmap.egg-info/dependency_links.txt
z2labelmap.egg-info/not-zip-safe
z2labelmap.egg-info/requires.txt
z2labelmap.egg-info/top_level.txt