Metadata-Version: 1.0
Name: z2labelmap
Version: 2.0.1
Summary: Convert lh/rh z-score vector to FreeSurfer labelmap
Home-page: https://github.com/FNNDSC/pl-z2labelmap
Author: Rudolph Pienaar
Author-email: rudolph.pienaar@gmail.com
License: MIT
Platform: UNKNOWN
